{
  "company_name": "Mi Pyme Digital",
  "industry": "Software and digital services",
  "products_services": "Website development, business automation, digital onboarding, and technical support for small businesses.",
  "location": "Lima, Peru",
  "years_operating": 6,
  "previous_contract_experience": "Delivered more than 200 digital projects for small businesses. Example: website and onboarding implementation valued at S/ 45,000 completed in 2025.",
  "certifications": "No ISO certifications. Team members have software engineering and cloud platform credentials.",
  "typical_project_size": 30000,
  "maximum_project_size": 150000,
  "employees": 8
}
